[
  {
    "nickname": "와인은 맛있어",
    "heartCount": 235,
    "reviewTitle": "집에서 가족들과 함께한 와인",
    "reviewContents": "헤헤헤 히ㅣ히 호호호 ~~~ 선물 받은 와인인데 넘 많이 달지도 않고 그렇다고 쓰지도 않고 적당하니 좋아요~~",
    "reviewimage": ["review_0_0", "review_0_1", "review_0_2"],
    "wineName": "산테로 피노 샤르도네 스푸만테",
    "price": "14000원",
    "hashTag": ["스파클링", "선물용", "가족모임"]
  },
  {
    "nickname": "와인은 절거워",
    "heartCount": 125,
    "reviewTitle": "홈파티 했어효♥",
    "reviewContents": "아로마는 체리향이구여 오크향도 조금 나는거 같아요 산도가 좀 있어서 신맛이 강하게 나요 가격대비 적당한거같아요~~",
    "reviewimage": ["review_1_0"],
    "wineName": "아델리나 쉬라즈 마타로",
    "price": "36000원",
    "hashTag": ["레드와인", "홈파티", "한정생산와인"]
  },
  {
    "nickname": "야호",
    "heartCount": 15,
    "reviewTitle": "즐거운 연말 파티~~ 와구 횐님덜과 함께♥",
    "reviewContents": "너무너무너무너무너무 즐거웠어요 헤헤헤 히ㅣ히 호호호 ~~~ 어제은ㄴ 가성비 짱! 자ㅉ아ㅉㅇ!!!!!룰루랄룰라루랄ㄹ",
    "reviewimage": ["review_2_0", "review_2_1"],
    "wineName": "레디페제",
    "price": "38000원",
    "hashTag": ["레드와인", "데일리와인"]
  },
  {
    "nickname": "뀨뀨꺄꺄",
    "heartCount": 37,
    "reviewTitle": "남친이랑 기념일에♥",
    "reviewContents": "남자친구 생일 기념으로 산 와인인데 파스타랑 먹으니까 완전 맛있었어요~!!!",
    "reviewimage": ["review_3_0", "review_3_1"],
    "wineName": "아방트 샤르도네",
    "price": "21000원",
    "hashTag": ["화이트", "취향저격", "선물용"]
  },
  {
    "nickname": "와린이",
    "heartCount": 23,
    "reviewTitle": "와린이 처음 마셔본 와인",
    "reviewContents": "와인은 처음인데 너무 달거나 맛이 강하지 않고 좋아요 스파클링이라 여름에도 마시기 좋을거같아요",
    "reviewimage": ["review_4_0", "review_4_1", "review_4_2"],
    "wineName": "알파카 브뤼",
    "price": "15000원",
    "hashTag": ["스파클링", "가성비와인", "와린이"]
  },
  {
    "nickname": "민트체크무늬와선생",
    "heartCount": 57,
    "reviewTitle": "여자친구와 함께 마신 로제 와인",
    "reviewContents": "병이 특이하고 이뻐서 좋아요 디저트 와인이라 그런지 안주 없이 그냥 먹어도 될만큼 깔끔한 와인이에요",
    "reviewimage": ["review_5_0"],
    "wineName": "에이 투 지 오레곤 버블스 로제",
    "price": "39000원",
    "hashTag": ["로제와인", "선물받았어요"]
  },
  {
    "nickname": "ㅇㅅㅇ",
    "heartCount": 11,
    "reviewTitle": "TRIMBACH RIESLING 추천합니다.",
    "reviewContents": "세계 10대 화이트 와인이라 그런지 균형 잡힌 맛이였어요. 마트 행사 하게 되면 재구매 할거같아요",
    "reviewimage": ["review_6_0"],
    "wineName": "트림바크 리슬링",
    "price": "28000원",
    "hashTag": ["프랑스와인", "내돈내산"]
  },
  {
    "nickname": "소복치",
    "heartCount": 15,
    "reviewTitle": "편의점에서 쓱 구매한 와인",
    "reviewContents": "갑자기 와인이 너무 먹고 싶어서 편의점 가서 마트에서 자주 봤던 와인이 있길래 한번 구매해봤는데 생각보다 괜찮은거같아요.",
    "reviewimage": ["review_7_0", "review_7_1", "review_7_2"],
    "wineName": "디아블로 샤르도네",
    "price": "9900원",
    "hashTag": ["가성비와인", "마트와인"]
  },
  {
    "nickname": "야호",
    "heartCount": 15,
    "reviewTitle": "즐거운 연말 파티~~ 와구 횐님덜과 함께♥",
    "reviewContents": "너무너무너무너무너무 즐거웠어요 헤헤헤 히ㅣ히 호호호 ~~~ 어제은ㄴ 가성비 짱! 자ㅉ아ㅉㅇ!!!!!룰루랄룰라루랄ㄹ",
    "reviewimage": ["review_2_0", "review_2_1"],
    "wineName": "레디페제",
    "price": "38000원",
    "hashTag": ["레드와인", "데일리와인"]
  },
  {
    "nickname": "와인은 맛있어",
    "heartCount": 235,
    "reviewTitle": "집에서 가족들과 함께한 와인",
    "reviewContents": "헤헤헤 히ㅣ히 호호호 ~~~ 선물 받은 와인인데 넘 많이 달지도 않고 그렇다고 쓰지도 않고 적당하니 좋아요~~",
    "reviewimage": ["review_0_0", "review_0_1", "review_0_2"],
    "wineName": "산테로 피노 샤르도네 스푸만테",
    "price": "14000원",
    "hashTag": ["스파클링", "선물용", "가족모임"]
  },
  {
    "nickname": "와인은 절거워",
    "heartCount": 125,
    "reviewTitle": "홈파티 했어효♥",
    "reviewContents": "아로마는 체리향이구여 오크향도 조금 나는거 같아요 산도가 좀 있어서 신맛이 강하게 나요 가격대비 적당한거같아요~~",
    "reviewimage": ["review_1_0"],
    "wineName": "아델리나 쉬라즈 마타로",
    "price": "36000원",
    "hashTag": ["레드와인", "홈파티", "한정생산와인"]
  },
  {
    "nickname": "민트체크무늬와선생",
    "heartCount": 57,
    "reviewTitle": "여자친구와 함께 마신 로제 와인",
    "reviewContents": "병이 특이하고 이뻐서 좋아요 디저트 와인이라 그런지 안주 없이 그냥 먹어도 될만큼 깔끔한 와인이에요",
    "reviewimage": ["review_5_0"],
    "wineName": "에이 투 지 오레곤 버블스 로제",
    "price": "39000원",
    "hashTag": ["로제와인", "선물받았어요"]
  },
  {
    "nickname": "뀨뀨꺄꺄",
    "heartCount": 37,
    "reviewTitle": "남친이랑 기념일에♥",
    "reviewContents": "남자친구 생일 기념으로 산 와인인데 파스타랑 먹으니까 완전 맛있었어요~!!!",
    "reviewimage": ["review_3_0", "review_3_1"],
    "wineName": "아방트 샤르도네",
    "price": "21000원",
    "hashTag": ["화이트", "취향저격", "선물용"]
  },
  {
    "nickname": "와린이",
    "heartCount": 23,
    "reviewTitle": "와린이 처음 마셔본 와인",
    "reviewContents": "와인은 처음인데 너무 달거나 맛이 강하지 않고 좋아요 스파클링이라 여름에도 마시기 좋을거같아요",
    "reviewimage": ["review_4_0", "review_4_1", "review_4_2"],
    "wineName": "알파카 브뤼",
    "price": "15000원",
    "hashTag": ["스파클링", "가성비와인", "와린이"]
  },

  {
    "nickname": "ㅇㅅㅇ",
    "heartCount": 11,
    "reviewTitle": "TRIMBACH RIESLING 추천합니다.",
    "reviewContents": "세계 10대 화이트 와인이라 그런지 균형 잡힌 맛이였어요. 마트 행사 하게 되면 재구매 할거같아요",
    "reviewimage": ["review_6_0"],
    "wineName": "트림바크 리슬링",
    "price": "28000원",
    "hashTag": ["프랑스와인", "내돈내산"]
  },

  {
    "nickname": "와인은 맛있어",
    "heartCount": 235,
    "reviewTitle": "집에서 가족들과 함께한 와인",
    "reviewContents": "헤헤헤 히ㅣ히 호호호 ~~~ 선물 받은 와인인데 넘 많이 달지도 않고 그렇다고 쓰지도 않고 적당하니 좋아요~~",
    "reviewimage": ["review_0_0", "review_0_1", "review_0_2"],
    "wineName": "산테로 피노 샤르도네 스푸만테",
    "price": "14000원",
    "hashTag": ["스파클링", "선물용", "가족모임"]
  },
  {
    "nickname": "와인은 절거워",
    "heartCount": 125,
    "reviewTitle": "홈파티 했어효♥",
    "reviewContents": "아로마는 체리향이구여 오크향도 조금 나는거 같아요 산도가 좀 있어서 신맛이 강하게 나요 가격대비 적당한거같아요~~",
    "reviewimage": ["review_1_0"],
    "wineName": "아델리나 쉬라즈 마타로",
    "price": "36000원",
    "hashTag": ["레드와인", "홈파티", "한정생산와인"]
  },
  {
    "nickname": "야호",
    "heartCount": 15,
    "reviewTitle": "즐거운 연말 파티~~ 와구 횐님덜과 함께♥",
    "reviewContents": "너무너무너무너무너무 즐거웠어요 헤헤헤 히ㅣ히 호호호 ~~~ 어제은ㄴ 가성비 짱! 자ㅉ아ㅉㅇ!!!!!룰루랄룰라루랄ㄹ",
    "reviewimage": ["review_2_0", "review_2_1"],
    "wineName": "레디페제",
    "price": "38000원",
    "hashTag": ["레드와인", "데일리와인"]
  },
  {
    "nickname": "소복치",
    "heartCount": 15,
    "reviewTitle": "편의점에서 쓱 구매한 와인",
    "reviewContents": "갑자기 와인이 너무 먹고 싶어서 편의점 가서 마트에서 자주 봤던 와인이 있길래 한번 구매해봤는데 생각보다 괜찮은거같아요.",
    "reviewimage": ["review_7_0", "review_7_1", "review_7_2"],
    "wineName": "디아블로 샤르도네",
    "price": "9900원",
    "hashTag": ["가성비와인", "마트와인"]
  },
  {
    "nickname": "뀨뀨꺄꺄",
    "heartCount": 37,
    "reviewTitle": "남친이랑 기념일에♥",
    "reviewContents": "남자친구 생일 기념으로 산 와인인데 파스타랑 먹으니까 완전 맛있었어요~!!!",
    "reviewimage": ["review_3_0", "review_3_1"],
    "wineName": "아방트 샤르도네",
    "price": "21000원",
    "hashTag": ["화이트", "취향저격", "선물용"]
  },
  {
    "nickname": "ㅇㅅㅇ",
    "heartCount": 11,
    "reviewTitle": "TRIMBACH RIESLING 추천합니다.",
    "reviewContents": "세계 10대 화이트 와인이라 그런지 균형 잡힌 맛이였어요. 마트 행사 하게 되면 재구매 할거같아요",
    "reviewimage": ["review_6_0"],
    "wineName": "트림바크 리슬링",
    "price": "28000원",
    "hashTag": ["프랑스와인", "내돈내산"]
  },
  {
    "nickname": "와린이",
    "heartCount": 23,
    "reviewTitle": "와린이 처음 마셔본 와인",
    "reviewContents": "와인은 처음인데 너무 달거나 맛이 강하지 않고 좋아요 스파클링이라 여름에도 마시기 좋을거같아요",
    "reviewimage": ["review_4_0", "review_4_1", "review_4_2"],
    "wineName": "알파카 브뤼",
    "price": "15000원",
    "hashTag": ["스파클링", "가성비와인", "와린이"]
  },
  {
    "nickname": "민트체크무늬와선생",
    "heartCount": 57,
    "reviewTitle": "여자친구와 함께 마신 로제 와인",
    "reviewContents": "병이 특이하고 이뻐서 좋아요 디저트 와인이라 그런지 안주 없이 그냥 먹어도 될만큼 깔끔한 와인이에요",
    "reviewimage": ["review_5_0"],
    "wineName": "에이 투 지 오레곤 버블스 로제",
    "price": "39000원",
    "hashTag": ["로제와인", "선물받았어요"]
  },

  {
    "nickname": "소복치",
    "heartCount": 15,
    "reviewTitle": "편의점에서 쓱 구매한 와인",
    "reviewContents": "갑자기 와인이 너무 먹고 싶어서 편의점 가서 마트에서 자주 봤던 와인이 있길래 한번 구매해봤는데 생각보다 괜찮은거같아요.",
    "reviewimage": ["review_7_0", "review_7_1", "review_7_2"],
    "wineName": "디아블로 샤르도네",
    "price": "9900원",
    "hashTag": ["가성비와인", "마트와인"]
  },
  {
    "nickname": "와인은 맛있어",
    "heartCount": 235,
    "reviewTitle": "집에서 가족들과 함께한 와인",
    "reviewContents": "헤헤헤 히ㅣ히 호호호 ~~~ 선물 받은 와인인데 넘 많이 달지도 않고 그렇다고 쓰지도 않고 적당하니 좋아요~~",
    "reviewimage": ["review_0_0", "review_0_1", "review_0_2"],
    "wineName": "산테로 피노 샤르도네 스푸만테",
    "price": "14000원",
    "hashTag": ["스파클링", "선물용", "가족모임"]
  },
  {
    "nickname": "야호",
    "heartCount": 15,
    "reviewTitle": "즐거운 연말 파티~~ 와구 횐님덜과 함께♥",
    "reviewContents": "너무너무너무너무너무 즐거웠어요 헤헤헤 히ㅣ히 호호호 ~~~ 어제은ㄴ 가성비 짱! 자ㅉ아ㅉㅇ!!!!!룰루랄룰라루랄ㄹ",
    "reviewimage": ["review_2_0", "review_2_1"],
    "wineName": "레디페제",
    "price": "38000원",
    "hashTag": ["레드와인", "데일리와인"]
  },
  {
    "nickname": "와인은 절거워",
    "heartCount": 125,
    "reviewTitle": "홈파티 했어효♥",
    "reviewContents": "아로마는 체리향이구여 오크향도 조금 나는거 같아요 산도가 좀 있어서 신맛이 강하게 나요 가격대비 적당한거같아요~~",
    "reviewimage": ["review_1_0"],
    "wineName": "아델리나 쉬라즈 마타로",
    "price": "36000원",
    "hashTag": ["레드와인", "홈파티", "한정생산와인"]
  },

  {
    "nickname": "뀨뀨꺄꺄",
    "heartCount": 37,
    "reviewTitle": "남친이랑 기념일에♥",
    "reviewContents": "남자친구 생일 기념으로 산 와인인데 파스타랑 먹으니까 완전 맛있었어요~!!!",
    "reviewimage": ["review_3_0", "review_3_1"],
    "wineName": "아방트 샤르도네",
    "price": "21000원",
    "hashTag": ["화이트", "취향저격", "선물용"]
  },

  {
    "nickname": "민트체크무늬와선생",
    "heartCount": 57,
    "reviewTitle": "여자친구와 함께 마신 로제 와인",
    "reviewContents": "병이 특이하고 이뻐서 좋아요 디저트 와인이라 그런지 안주 없이 그냥 먹어도 될만큼 깔끔한 와인이에요",
    "reviewimage": ["review_5_0"],
    "wineName": "에이 투 지 오레곤 버블스 로제",
    "price": "39000원",
    "hashTag": ["로제와인", "선물받았어요"]
  },
  {
    "nickname": "ㅇㅅㅇ",
    "heartCount": 11,
    "reviewTitle": "TRIMBACH RIESLING 추천합니다.",
    "reviewContents": "세계 10대 화이트 와인이라 그런지 균형 잡힌 맛이였어요. 마트 행사 하게 되면 재구매 할거같아요",
    "reviewimage": ["review_6_0"],
    "wineName": "트림바크 리슬링",
    "price": "28000원",
    "hashTag": ["프랑스와인", "내돈내산"]
  },
  {
    "nickname": "와인은 맛있어",
    "heartCount": 235,
    "reviewTitle": "집에서 가족들과 함께한 와인",
    "reviewContents": "헤헤헤 히ㅣ히 호호호 ~~~ 선물 받은 와인인데 넘 많이 달지도 않고 그렇다고 쓰지도 않고 적당하니 좋아요~~",
    "reviewimage": ["review_0_0", "review_0_1", "review_0_2"],
    "wineName": "산테로 피노 샤르도네 스푸만테",
    "price": "14000원",
    "hashTag": ["스파클링", "선물용", "가족모임"]
  },
  {
    "nickname": "와린이",
    "heartCount": 23,
    "reviewTitle": "와린이 처음 마셔본 와인",
    "reviewContents": "와인은 처음인데 너무 달거나 맛이 강하지 않고 좋아요 스파클링이라 여름에도 마시기 좋을거같아요",
    "reviewimage": ["review_4_0", "review_4_1", "review_4_2"],
    "wineName": "알파카 브뤼",
    "price": "15000원",
    "hashTag": ["스파클링", "가성비와인", "와린이"]
  },
  {
    "nickname": "소복치",
    "heartCount": 15,
    "reviewTitle": "편의점에서 쓱 구매한 와인",
    "reviewContents": "갑자기 와인이 너무 먹고 싶어서 편의점 가서 마트에서 자주 봤던 와인이 있길래 한번 구매해봤는데 생각보다 괜찮은거같아요.",
    "reviewimage": ["review_7_0", "review_7_1", "review_7_2"],
    "wineName": "디아블로 샤르도네",
    "price": "9900원",
    "hashTag": ["가성비와인", "마트와인"]
  },

  {
    "nickname": "와인은 절거워",
    "heartCount": 125,
    "reviewTitle": "홈파티 했어효♥",
    "reviewContents": "아로마는 체리향이구여 오크향도 조금 나는거 같아요 산도가 좀 있어서 신맛이 강하게 나요 가격대비 적당한거같아요~~",
    "reviewimage": ["review_1_0"],
    "wineName": "아델리나 쉬라즈 마타로",
    "price": "36000원",
    "hashTag": ["레드와인", "홈파티", "한정생산와인"]
  },
  {
    "nickname": "민트체크무늬와선생",
    "heartCount": 57,
    "reviewTitle": "여자친구와 함께 마신 로제 와인",
    "reviewContents": "병이 특이하고 이뻐서 좋아요 디저트 와인이라 그런지 안주 없이 그냥 먹어도 될만큼 깔끔한 와인이에요",
    "reviewimage": ["review_5_0"],
    "wineName": "에이 투 지 오레곤 버블스 로제",
    "price": "39000원",
    "hashTag": ["로제와인", "선물받았어요"]
  },
  {
    "nickname": "뀨뀨꺄꺄",
    "heartCount": 37,
    "reviewTitle": "남친이랑 기념일에♥",
    "reviewContents": "남자친구 생일 기념으로 산 와인인데 파스타랑 먹으니까 완전 맛있었어요~!!!",
    "reviewimage": ["review_3_0", "review_3_1"],
    "wineName": "아방트 샤르도네",
    "price": "21000원",
    "hashTag": ["화이트", "취향저격", "선물용"]
  },

  {
    "nickname": "소복치",
    "heartCount": 15,
    "reviewTitle": "편의점에서 쓱 구매한 와인",
    "reviewContents": "갑자기 와인이 너무 먹고 싶어서 편의점 가서 마트에서 자주 봤던 와인이 있길래 한번 구매해봤는데 생각보다 괜찮은거같아요.",
    "reviewimage": ["review_7_0", "review_7_1", "review_7_2"],
    "wineName": "디아블로 샤르도네",
    "price": "9900원",
    "hashTag": ["가성비와인", "마트와인"]
  },

  {
    "nickname": "와린이",
    "heartCount": 23,
    "reviewTitle": "와린이 처음 마셔본 와인",
    "reviewContents": "와인은 처음인데 너무 달거나 맛이 강하지 않고 좋아요 스파클링이라 여름에도 마시기 좋을거같아요",
    "reviewimage": ["review_4_0", "review_4_1", "review_4_2"],
    "wineName": "알파카 브뤼",
    "price": "15000원",
    "hashTag": ["스파클링", "가성비와인", "와린이"]
  },

  {
    "nickname": "야호",
    "heartCount": 15,
    "reviewTitle": "즐거운 연말 파티~~ 와구 횐님덜과 함께♥",
    "reviewContents": "너무너무너무너무너무 즐거웠어요 헤헤헤 히ㅣ히 호호호 ~~~ 어제은ㄴ 가성비 짱! 자ㅉ아ㅉㅇ!!!!!룰루랄룰라루랄ㄹ",
    "reviewimage": ["review_2_0", "review_2_1"],
    "wineName": "레디페제",
    "price": "38000원",
    "hashTag": ["레드와인", "데일리와인"]
  },
  {
    "nickname": "ㅇㅅㅇ",
    "heartCount": 11,
    "reviewTitle": "TRIMBACH RIESLING 추천합니다.",
    "reviewContents": "세계 10대 화이트 와인이라 그런지 균형 잡힌 맛이였어요. 마트 행사 하게 되면 재구매 할거같아요",
    "reviewimage": ["review_6_0"],
    "wineName": "트림바크 리슬링",
    "price": "28000원",
    "hashTag": ["프랑스와인", "내돈내산"]
  }
]
